branchkey/__consumer.py
branchkey/__init__.py
branchkey/client.py
branchkey/utils.py
branchkey-2.8.0.dist-info/METADATA
branchkey-2.8.0.dist-info/WHEEL
branchkey-2.8.0.dist-info/top_level.txt
branchkey-2.8.0.dist-info/RECORD
