Metadata-Version: 2.1
Name: branchkey
Version: 2.8.0
Summary: Client application to interface with the BranchKey system
Home-page: https://branchkey.com
Author: BranchKey
Author-email: info@branchkey.com
Project-URL: Homepage, https://branchkey.com
Project-URL: Repository, https://gitlab.com/branchkey/client_application
Classifier: Programming Language :: Python :: 3
Classifier: License :: OSI Approved :: MIT License
Classifier: Operating System :: OS Independent
Requires-Python: >=3.6
Requires-Dist: requests
Requires-Dist: numpy
Requires-Dist: pika
Requires-Dist: responses
Requires-Dist: pysocks
